{
  "title": "Agenda Ransomware Exploits MeshAgent and WSL for Cross-Platform Attacks",
  "date": "Jul 2025",
  "url": "https://x.com/TrendMicroRSRCH/status/1942720354390081694",
  "tags": [
    "Ransomware",
    "Cross-Platform",
    "Defense Evasion"
  ],
  "description": "Thread on Agenda ransomware exploiting MeshAgent and Windows Subsystem for Linux (WSL) to deploy Linux payloads on Windows systems, raising the bar for cross-platform sophistication.",
  "source": "X/Twitter (@TrendMicroRSRCH)",
  "type": "microstory",
  "order": 17
}
